graspclutter6dAPI/__init__.py
graspclutter6dAPI/grasp.py
graspclutter6dAPI/graspclutter6d.py
graspclutter6dAPI/graspclutter6d_eval.py
graspclutter6dAPI/utils/__init__.py
graspclutter6dAPI/utils/config.py
graspclutter6dAPI/utils/eval_utils.py
graspclutter6dAPI/utils/pose.py
graspclutter6dAPI/utils/rotation.py
graspclutter6dAPI/utils/trans3d.py
graspclutter6dAPI/utils/utils.py
graspclutter6dAPI/utils/vis.py
graspclutter6dAPI/utils/xmlhandler.py
graspclutter6dAPI/utils/dexnet/__init__.py
graspclutter6dAPI/utils/dexnet/abstractstatic.py
graspclutter6dAPI/utils/dexnet/constants.py
graspclutter6dAPI/utils/dexnet/grasping/__init__.py
graspclutter6dAPI/utils/dexnet/grasping/contacts.py
graspclutter6dAPI/utils/dexnet/grasping/grasp.py
graspclutter6dAPI/utils/dexnet/grasping/grasp_quality_config.py
graspclutter6dAPI/utils/dexnet/grasping/grasp_quality_function.py
graspclutter6dAPI/utils/dexnet/grasping/graspable_object.py
graspclutter6dAPI/utils/dexnet/grasping/quality.py
graspclutter6dAPI/utils/dexnet/grasping/meshpy/__init__.py
graspclutter6dAPI/utils/dexnet/grasping/meshpy/mesh.py
graspclutter6dAPI/utils/dexnet/grasping/meshpy/obj_file.py
graspclutter6dAPI/utils/dexnet/grasping/meshpy/sdf.py
graspclutter6dAPI/utils/dexnet/grasping/meshpy/sdf_file.py
graspclutter6dAPI/utils/dexnet/grasping/meshpy/stable_pose.py
graspclutter6dAPI-0.0.2.dist-info/METADATA
graspclutter6dAPI-0.0.2.dist-info/WHEEL
graspclutter6dAPI-0.0.2.dist-info/top_level.txt
graspclutter6dAPI-0.0.2.dist-info/RECORD
